{"":{"language":"es","plural-forms":"nplurals=2; plural=(n > 1);"}
,"specialaj signoj ne rajtas en pasvorto": "no se permiten caracteres especiales en la contraseña"
,"Ĉi tiu kampo estas deviga": "Este campo es obligatorio"
,"specialaj signoj ne rajtas en la nomo de kamerao": "no se permiten caracteres especiales en el nombre de la cámara"
,"valoro devas esti multoblo de 8": "el valor debe ser un múltiplo de 8"
,"specialaj signoj ne rajtas en radika voja nomo": "no se permiten caracteres especiales en el nombre de la ruta raíz"
,"dosieroj ne povas esti kreitaj rekte en la radiko de via sistemo": "los archivos no se pueden crear directamente en la raíz de su sistema"
,"enigu validan retpoŝtadreson": "ingrese una dirección de correo electrónico válida"
,"enigu liston de koma apartaj validaj retpoŝtadresoj": "ingrese una lista de direcciones de correo electrónico válidas separadas por comas"
,"specialaj signoj ne rajtas en dosiernomo": "no se permiten caracteres especiales en el nombre del archivo"
,"enigu validan valoron": "ingrese un valor válido"
,"Ĉi rekursie forigos ĉiujn dosierojn ĉeestantajn en la nuba dosierujo \"": "Esto eliminará recursivamente todos los archivos en la carpeta de la nube \""
,"\", ne nur tiuj alŝutitaj de motionEye!": "\", no solo los subidos por motionEye!"
,"Ĉi rekursie forigos ĉiujn malnovajn amaskomunikilajn dosierojn en la dosierujo \"": "Esto de forma recursiva eliminará todos los archivos multimedia antiguos en la carpeta \""
,"\", ne nur tiuj kreitaj de motionEye!": "\", no solo los creados por motionEye!"
,"Ne eblas redakti la maskon sen valida kameraa bildo!": "¡No se puede editar la máscara sin una imagen de cámara válida!"
,"Propra": "Propio"
,"Propra dosierindiko": "Nombre de archivo personalizado"
,"Retan kunlokon": "Comunicación en línea"
,"Via retumilo ne efektivigas ĉi tiun funkcion!": "¡Su navegador no realiza esta característica!"
,"Apliki": "Aplicar"
,"Certigu, ke ĉiuj agordaj opcioj validas!": "¡Asegúrese de que todas las opciones de configuración sean válidas!"
,"Ĉi tio rekomencos la sistemon. Daŭrigi?": "Esto reiniciará el sistema. Continuar?"
,"Vere fermiti sistemon?": "¿Realmente apagó el sistema?"
,"Malŝaltita": "Apagado"
,"Ĉu vere restartigi ?": "¿Realmente reiniciar?"
,"La sistemo rekomencis!": "¡El sistema se reinició!"
,"Bonvolu apliki unue la modifitajn agordojn!": "¡Primero aplique la configuración modificada!"
,"Neniu fotilo por forigi!": "No hay cámara para quitar!"
,"Ĉu forigi kameraon ": "Puede quitar la cámara"
,"motionEye estas ĝisdatigita (aktuala versio: ": "motionEye se actualiza (versión actual:"
,"Nova versio havebla: ": "Nueva versión disponible:"
,". Ĝisdatigi?": ". Actualización?"
,"motionEye estis sukcese ĝisdatigita!": "motionEye ha sido actualizado con éxito!"
,"Ĝisdatigo malsukcesis!": "¡Actualización fallida!"
,"La ĝisdatiga procezo malsukcesis!": "¡El proceso de actualización falló!"
,"Rezerva dosiero": "Archivo de respaldo"
,"La rezervan dosieron, kiun vi antaŭe elŝutis.": "El archivo de respaldo que descargó anteriormente."
,"Restaŭrigi Agordon": "Restaurar configuración"
,"Restaŭriganta agordon ...": "Restaurando la configuración ..."
,"La agordo restaŭrigis!": "¡La configuración ha sido restaurada!"
,"Malsukcesis restaŭri la agordon!": "¡Error al restaurar la configuración!"
,"Aliri la alŝutan servon malsukcesis: ": "Error al acceder al servicio de carga:"
,"Aliri la alŝutan servon sukcesis!": "¡El acceso al servicio de carga fue exitoso!"
,"Sciiga retpoŝto fiaskis:": "News Correo electrónico falló:"
,"Certiĝu, ke ĉiuj agordaj opcioj estas validaj!": "¡Asegúrese de que todas las opciones de configuración sean válidas!"
,"Sciiga Telegramo fiaskis:": "Falló el telegrama de notificación:"
,"Sciiga Telegramo sukcesis!": "¡El telegrama de notificación fue exitoso!"
,"Aliro al retdividado fiaskis: ": "El acceso a la transmisión de red falló:"
,"Aliro al retdividado sukcesis!": "¡El acceso a la retardación ha sido exitoso!"
,"Ĉu vere forigi ĉi tiun dosieron?": "¿Realmente borrar este archivo?"
,"Ĉu vere forigi ĉiujn bildojn de \"%(group)s\"?": "¿Eliminar realmente todas las imágenes de \"%(group)s\"?"
,"Ĉu vere forigi ĉiujn filmojn de \"%(group)s\"?": "¿Eliminar realmente todas las películas de \"%(group)s\"?"
,"Ĉu vere forigi ĉiujn ne grupigitajn bildojn?": "¿Eliminar realmente todas las imágenes desagrupadas?"
,"Ĉu vere forigi ĉiujn ne grupigitajn filmojn?": "¿Eliminar realmente todas las películas desagrupadas?"
,"aldonadi kameraon...": "agregar cámara ..."
,"bone": "esta bien"
,"Uzantnomo": "Nombre de usuario"
,"Pasvorto": "Contraseña"
,"Memoru min": "Recuerdame"
,"Ensaluti": "Iniciar sesión"
,"Nuligi": "Cancelar"
,"Vi abortis la filmeton.": "Abortaste el video."
,"Reto eraro okazis.": "Se produjo un error de red."
,"Malkodado-eraro aŭ neprogresinta funkcio.": "Error de decodificación o función no proyectada."
,"Formato ne subtenata aŭ neatingebla/netaŭga por ludado.": "Formato no compatible o inaccesible / inadecuado para la reproducción."
,"Nekonata eraro okazis.": "Ocurrió un error desconocido."
,"Eraro : ": "Error:"
,"antaŭa bildo": "imagen anterior"
,"ludi": "jugar"
,"ludi * 5 kaj enĉenigi": "jugar * 5 y encadenar"
,"sekva bildo": "siguiente imagen"
,"Fermi": "Cerrar"
,"Elŝuti": "Descargar"
,"Forigi": "Eliminar"
,"Kamerao tipo": "Tipo de cámara"
,"Loka V4L2-kamerao": "Cámara local V4L2"
,"Loka MMAL-kamerao": "Cámara MMAL local"
,"Reta kamerao": "Webcam"
,"Fora motionEye kamerao": "Cámara de movimiento exterior"
,"Simpla MJPEG-kamerao": "Cámara simple MJPEG"
,"la speco de kamerao, kiun vi volas aldoni": "el tipo de cámara que desea agregar"
,"URL": "URL"
,"http://ekzemplo.com:8765/cams/...": "http: //example.com: 8765 / cams / ..."
,"la kameraa URL (ekz. http://ekzemplo.com:8080/cam/)": "la URL de la cámara (por ejemplo, http://example.com:8080/cam/)"
,"uzantnomo...": "nombre de usuario ..."
,"la uzantnomo por la URL, se bezonata (ekz. administranto)": "el nombre de usuario para la URL, si es necesario (por ejemplo, administrador)"
,"pasvorto...": "contraseña ..."
,"la pasvorto por la URL, se bezonata": "la contraseña de la URL, si es necesario"
,"Kamerao": "Cámara"
,"la kameraon, kiun vi volas aldoni": "la cámara que quieres agregar"
,"Fora motionEye kamerao estas kameraoj instalitaj malantaŭ alia servilo de MotionEye. Aldonante ilin ĉi tie permesos vin rigardi kaj administri ilin de malproksime.": "Una cámara motionEye distante son cámaras instaladas detrás de otro servidor MotionEye. Agregarlos aquí le permitirá verlos y administrarlos desde la distancia."
,"Retaj kameraoj (aŭ IP-kameraoj) estas aparatoj, kiuj denaske fluas RTSP/RTMP aŭ MJPEG-filmetojn aŭ simplajn JPEG-bildojn. Konsultu la manlibron de via aparato por ekscii la ĝustan URL RTSP, RTMP, MJPEG aŭ JPEG.": "Las cámaras de red (o cámaras IP) son dispositivos que transmiten de forma nativa videos RTSP / RTMP o MJPEG o imágenes JPEG simples. Consulte el manual de su dispositivo para averiguar la URL correcta de RTSP, RTMP, MJPEG o JPEG."
,"Lokaj MMAL-kameraoj estas aparatoj konektitaj rekte al via motionEye-sistemo. Ĉi tiuj estas kutime kart-specifaj kameraoj.": "Las cámaras MMAL locales son dispositivos que están conectados directamente a su sistema motionEye. Estas suelen ser cámaras específicas para tarjetas."
,"Aldonante vian aparaton kiel simplan MJPEG-kameraon anstataŭ kiel retan kameraon plibonigos la fotografaĵon, sed neniu moviĝo-detekto, bilda kaptado aŭ registrado de filmoj estos disponebla por ĝi. La kamerao devas esti alirebla por via servilo kaj via retumilo. Ĉi tiu tipo de kamerao ne kongruas kun Internet Explorer.": "Agregar su dispositivo como una simple cámara MJPEG en lugar de una cámara web mejorará la fotografía, pero no estará disponible la detección de movimiento, captura de imágenes o grabación de películas. La cámara debe ser accesible para su servidor y su navegador. Este tipo de cámara no coincide con Internet Explorer."
,"Lokaj V4L2-kameraoj estas kameraaj aparatoj konektitaj rekte al via motionEye-sistemo, kutime per USB.": "Las cámaras locales V4L2 son dispositivos de cámara conectados directamente a su sistema motionEye, generalmente a través de USB."
,"Aldonadi kameraon...": "Agregar cámara ..."
,"Grupo": "Grupo"
,"Inkluzivi foton prenitan ĉiun": "Incluya una foto tomada cada uno"
,"sekundo": "segundo"
,"5 sekundoj": "5 segundos"
,"10 sekundoj": "10 segundos"
,"30 sekundoj": "30 segundos"
,"minuto": "minuto"
,"5 minutoj": "5 minutos"
,"10 minutoj": "10 minutos"
,"30 minutoj": "30 minutos"
,"horo": "una hora"
,"Elektu la intervalon de tempo inter du elektitaj bildoj.": "Seleccione el intervalo de tiempo entre dos imágenes seleccionadas."
,"Filmo framfrekvenco": "Velocidad de fotogramas de la película"
,"Elektu kiom rapide vi volas ke la akselita video estu.": "Elija qué tan rápido desea que sea el video acelerado."
,"Konsiderante la grandan nombron da bildoj, krei vian video povus daŭri iom da tempo!": "Teniendo en cuenta la gran cantidad de imágenes, ¡crear su video podría tomar algún tiempo!"
,"Krei akselita video": "Crea un video acelerado"
,"Filmo kreanta en progreso...": "Una película en progreso ..."
,"Zipitaj": "Con cremallera"
,"Akselita video": "Video acelerado"
,"Forigi ĉiujn": "Eliminarlos todos"
,"Bildoj prenitaj de ": "Fotografías tomadas por"
,"Filmoj registritaj de ": "Películas grabadas por"
,"montru ĉi tiun fotilon plenekranan": "Mostrar esta cámara a tiempo completo"
,"montri ĉiujn fotilojn": "Mostrar todas las cámaras"
,"montru nur ĉi tiun fotilon": "Mostrar solo esta cámara"
,"malfermaj bildoj retumilo": "abrir el navegador de imágenes"
,"malferma videoj retumilo": "abrir navegador de videos"
,"agordi ĉi tiun kameraon": "configurar esta cámara"
,"preni instantaron": "tomar una instantánea"
,"Vi ankoraŭ ne agordis iun kameraon. Alklaku ĉi tie por aldoni unu ...": "Aún no has configurado ninguna cámara. Haga clic aquí para añadir uno ..."
,"enigu pozitivan nombron": "ingrese un número positivo"
,"enigu pozitivan entjeran nombron": "ingrese un entero positivo"
,"enigu nombron": "ingrese un número"
,"enigu entjeran nombron": "ingrese un número entero"
," inter ": "en el medio"
," kaj ": "y"
," pli ol ": "mas que"
," malpli ol ": "menos de"
,"enigu validan tempon en la sekva formato: HH:MM": "ingrese el tiempo válido en el siguiente formato: HH: MM"
,"enigu validan URL (ekz. http://ekzemplo.com:8080/cams/)": "ingrese una URL válida (por ejemplo, http://example.com:8080/cams/)"
,"fermi": "para cerrar"
,"Ne": "No"
,"Jes": "Si"
,"Bone": "Esta bien"
}
